{
  "_type": "export",
  "__export_format": 4,
  "__export_date": "2023-03-01T13:24:08.177Z",
  "__export_source": "insomnia.desktop.app:v2022.7.5",
  "resources": [
    {
      "_id": "req_e31a8c7460e54a5982dab711a9ed1476",
      "parentId": "wrk_e340c12e993847aba4ac4c587d5d9df3",
      "modified": 1677627789482,
      "created": 1677627789482,
      "url": "http://localhost:8080",
      "name": "home",
      "description": "",
      "method": "GET",
      "body": {},
      "parameters": [],
      "headers": [],
      "authentication": {},
      "metaSortKey": -1677627789483,
      "isPrivate": false,
      "settingStoreCookies": true,
      "settingSendCookies": true,
      "settingDisableRenderRequestBody": false,
      "settingEncodeUrl": true,
      "settingRebuildPath": true,
      "settingFollowRedirects": "global",
      "_type": "request"
    },
    {
      "_id": "wrk_e340c12e993847aba4ac4c587d5d9df3",
      "parentId": null,
      "modified": 1677627786007,
      "created": 1677627786007,
      "name": "Bookings",
      "description": "",
      "scope": "collection",
      "_type": "workspace"
    },
    {
      "_id": "req_39ccfaaf9ef44fc6becf34da3ccf13ed",
      "parentId": "wrk_e340c12e993847aba4ac4c587d5d9df3",
      "modified": 1677675755594,
      "created": 1677675755594,
      "url": "http://localhost:8080/about",
      "name": "about",
      "description": "",
      "method": "GET",
      "body": {},
      "parameters": [],
      "headers": [],
      "authentication": {},
      "metaSortKey": -1677675755594,
      "isPrivate": false,
      "settingStoreCookies": true,
      "settingSendCookies": true,
      "settingDisableRenderRequestBody": false,
      "settingEncodeUrl": true,
      "settingRebuildPath": true,
      "settingFollowRedirects": "global",
      "_type": "request"
    },
    {
      "_id": "req_7bbbf7f7ee89431c87116710ade5e1eb",
      "parentId": "wrk_e340c12e993847aba4ac4c587d5d9df3",
      "modified": 1677676776138,
      "created": 1677676776138,
      "url": "http://localhost:8080/divide",
      "name": "New Request",
      "description": "",
      "method": "GET",
      "body": {},
      "parameters": [],
      "headers": [],
      "authentication": {},
      "metaSortKey": -1677676776138,
      "isPrivate": false,
      "settingStoreCookies": true,
      "settingSendCookies": true,
      "settingDisableRenderRequestBody": false,
      "settingEncodeUrl": true,
      "settingRebuildPath": true,
      "settingFollowRedirects": "global",
      "_type": "request"
    },
    {
      "_id": "env_90007c345ab572cca7dd8568b8ff56d644bd0294",
      "parentId": "wrk_e340c12e993847aba4ac4c587d5d9df3",
      "modified": 1677627786010,
      "created": 1677627786010,
      "name": "Base Environment",
      "data": {},
      "dataPropertyOrder": null,
      "color": null,
      "isPrivate": false,
      "metaSortKey": 1677627786010,
      "_type": "environment"
    },
    {
      "_id": "spc_b17a3261ad724efba05676ebf233354e",
      "parentId": "wrk_e340c12e993847aba4ac4c587d5d9df3",
      "modified": 1677627786008,
      "created": 1677627786008,
      "fileName": "Golang 1",
      "contents": "",
      "contentType": "yaml",
      "_type": "api_spec"
    }
  ]
}
